cyprian_datetime/__init__.py
cyprian_datetime/concordance.py
cyprian_datetime/constants.py
cyprian_datetime/cyprian_date.py
cyprian_datetime/cyprian_datetime.py
cyprian_datetime/frontend_utils.py
cyprian_datetime/sql/create_drop.sql
cyprian_datetime-1.1.0.data/scripts/get-cyprian-date
cyprian_datetime-1.1.0.dist-info/METADATA
cyprian_datetime-1.1.0.dist-info/WHEEL
cyprian_datetime-1.1.0.dist-info/top_level.txt
cyprian_datetime-1.1.0.dist-info/RECORD
