Metadata-Version: 2.1
Name: cyprian-datetime
Version: 1.1.0
Summary: A Cyprian extension to the datetime package
Home-page: https://github.com/tomhosker/cyprian_datetime
Author: Tom Hosker
Author-email: tomdothosker@gmail.com
License: MIT
Requires-Dist: ephem
Requires-Dist: hosker-utils
